redis_workers/__init__.py
redis_workers/redis_worker.py
redis_workers-0.1.1.dist-info/METADATA
redis_workers-0.1.1.dist-info/WHEEL
redis_workers-0.1.1.dist-info/top_level.txt
redis_workers-0.1.1.dist-info/RECORD
