Metadata-Version: 2.1
Name: redis-workers
Version: 0.1.1
Summary: A tool that simplifies Redis usage for repeating tasks
Home-page: https://github.com/realiti4/redis-worker
Author: Onur Cetinkol
Author-email: realiti44@gmail.com
Classifier: Programming Language :: Python :: 3
Classifier: License :: OSI Approved :: MIT License
Classifier: Operating System :: OS Independent
Requires-Python: >=3.9
Requires-Dist: redis
